{
  "parent": "mythicmetals:carmot",
  "display": {
    "title": {
      "translate": "advancement.mythicmetals.carmot_staff.title"
    },
    "description": {
      "translate": "advancement.mythicmetals.carmot_staff.description"
    },
    "icon": {
      "item": "mythicmetals:carmot_staff"
    },
    "frame": "goal",
    "show_toast": true,
    "announce_to_chat": true,
    "hidden": false
  },
  "criteria": {
    "mythical_magical_staffnite": {
      "trigger": "minecraft:inventory_changed",
      "conditions": {
        "items": [
          {
            "items": [
              "mythicmetals:carmot_staff"
            ]
          }
        ]
      }
    }
  }
}